__init__.py
di.py
fe_python_di-0.2.0.dist-info/LICENSE
fe_python_di-0.2.0.dist-info/METADATA
fe_python_di-0.2.0.dist-info/WHEEL
fe_python_di-0.2.0.dist-info/top_level.txt
fe_python_di-0.2.0.dist-info/RECORD
