Metadata-Version: 2.1
Name: fe-python-di
Version: 0.2.0
Summary: Simple python dependency injection
Author-email: samizdam <samizdam@inbox.ru>
License-File: LICENSE
